CHANGES.txt
LICENSE.txt
MANIFEST.in
README.md
setup.py
imboclient/__init__.py
imboclient/client.py
imboclient.egg-info/PKG-INFO
imboclient.egg-info/SOURCES.txt
imboclient.egg-info/dependency_links.txt
imboclient.egg-info/requires.txt
imboclient.egg-info/top_level.txt
imboclient/header/__init__.py
imboclient/header/authenticate.py
imboclient/url/__init__.py
imboclient/url/accesstoken.py
imboclient/url/image.py
imboclient/url/images.py
imboclient/url/imagesquery.py
imboclient/url/metadata.py
imboclient/url/status.py
imboclient/url/url.py
imboclient/url/user.py