Metadata-Version: 1.0
Name: imboclient
Version: 0.0.1b0
Summary: Python client for Imbo
Home-page: http://www.imbo-project.org
Author: Andreas Søvik
Author-email: arsovik@gmail.com
License: LICENSE.txt
Platform: UNKNOWN
